daily_evapotranspiration_upscaling/__init__.py
daily_evapotranspiration_upscaling/daily_evapotranspiration_upscaling.py
daily_evapotranspiration_upscaling/version.py
daily_evapotranspiration_upscaling-1.1.0.dist-info/licenses/LICENSE
daily_evapotranspiration_upscaling-1.1.0.dist-info/METADATA
daily_evapotranspiration_upscaling-1.1.0.dist-info/WHEEL
daily_evapotranspiration_upscaling-1.1.0.dist-info/top_level.txt
daily_evapotranspiration_upscaling-1.1.0.dist-info/RECORD
