Metadata-Version: 2.4
Name: daily-evapotranspiration-upscaling
Version: 1.1.0
Summary: Instantaneous/Daily Evapotranspiration Upscaling Utilities Python Package
Author-email: "Gregory H. Halverson" <gregory.h.halverson@jpl.nasa.gov>
Project-URL: Homepage, https://github.com/JPL-Evapotranspiration-Algorithms/daily-evapotranspiration-upscaling
Classifier: Programming Language :: Python :: 3
Classifier: Operating System :: OS Independent
Requires-Python: >=3.10
License-File: LICENSE
Requires-Dist: numpy
Requires-Dist: pandas
Requires-Dist: python-dateutil
Requires-Dist: rasters
Requires-Dist: solar-apparent-time
Requires-Dist: sun-angles>=1.4.0
Requires-Dist: verma-net-radiation
Provides-Extra: dev
Requires-Dist: build; extra == "dev"
Requires-Dist: pytest>=6.0; extra == "dev"
Requires-Dist: pytest-cov; extra == "dev"
Requires-Dist: jupyter; extra == "dev"
Requires-Dist: pytest; extra == "dev"
Requires-Dist: twine; extra == "dev"
Dynamic: license-file
